azhida_tools/__init__.py
azhida_tools/mysql.py
azhida_tools/tool.py
azhida_tools-0.0.8.dist-info/METADATA
azhida_tools-0.0.8.dist-info/WHEEL
azhida_tools-0.0.8.dist-info/top_level.txt
azhida_tools-0.0.8.dist-info/RECORD
