Metadata-Version: 2.1
Name: azhida-tools
Version: 0.0.8
Summary: 常用工具包
Home-page: https://github.com/azhida/python-tools.git
Author: azhida
Author-email: 334064034@qq.com
License: UNKNOWN
Platform: UNKNOWN
Classifier: Programming Language :: Python :: 3
Classifier: License :: OSI Approved :: MIT License
Classifier: Operating System :: OS Independent
Requires-Python: >=3.6
